spf/__init__.py
spf/config.py
spf/context.py
spf/framework.py
spf/plugin.py
spf/plugins/__init__.py
spf/plugins/contextualize.py
Sanic_Plugins_Framework-0.9.4.post2.dist-info/LICENSE.txt
Sanic_Plugins_Framework-0.9.4.post2.dist-info/METADATA
Sanic_Plugins_Framework-0.9.4.post2.dist-info/WHEEL
Sanic_Plugins_Framework-0.9.4.post2.dist-info/entry_points.txt
Sanic_Plugins_Framework-0.9.4.post2.dist-info/top_level.txt
Sanic_Plugins_Framework-0.9.4.post2.dist-info/RECORD
