Metadata-Version: 2.1
Name: Sanic-Plugins-Framework
Version: 0.9.4.post2
Summary: Doing all of the boilerplate to create a Sanic Plugin, so you don't have to.
Home-page: https://github.com/ashleysommer/sanicpluginsframework
Author: Ashley Sommer
Author-email: ashleysommer@gmail.com
License: MIT
Platform: any
Classifier: Environment :: Web Environment
Classifier: Intended Audience :: Developers
Classifier: License :: OSI Approved :: MIT License
Classifier: Operating System :: OS Independent
Classifier: Programming Language :: Python
Classifier: Programming Language :: Python :: 3
Classifier: Programming Language :: Python :: 3.5
Classifier: Programming Language :: Python :: 3.6
Classifier: Programming Language :: Python :: 3.7
Classifier: Programming Language :: Python :: 3.8
Classifier: Programming Language :: Python :: Implementation :: CPython
Classifier: Programming Language :: Python :: Implementation :: PyPy
Classifier: Topic :: Internet :: WWW/HTTP :: Dynamic Content
Classifier: Topic :: Software Development :: Libraries :: Python Modules
Requires-Dist: setuptools (>=40.0)
Requires-Dist: sanic (<21,>=18.12.0)
